Workbook

Sheet START HERE
B2: NEXORA BUSINESS SERVICES — BUSINESS OPERATIONS & PERFORMANCE ANALYSIS
B4: PROJECT SUBTITLE | C4: Identifying Operational Inefficiencies, Measuring Business Performance, and Recommending Data-Driven Improvements
B5: ANALYST ROLE | C5: Junior Operations Analyst (Portfolio Simulation Project)
B6: INDUSTRY & SCENARIO | C6: Nexora Business Services is a mid-scale B2B operational support and service delivery firm. Across 12 months in 2025, leadership observed growing backlogs, uneven departmental delivery, and increasing operational expenditure. This project provides an end-to-end data audit, KPI evaluation, root-cause diagnostics, and actionable strategic recommendations.
B7: CORE BUSINESS QUESTIONS | C7: 1. Are operational targets being achieved across departments? 2. What are the primary bottlenecks driving service delays? 3. Where are operating costs escalating disproportionately to output? 4. What is the operational correlation between task delays and customer complaints? 5. What standardized standard operating procedures (SOPs) can restore target adherence?
B8: PROJECT WORKFLOW | C8: Raw Data Ingestion → Data Quality Audit & Cleaning → Multi-Level KPI Analysis → Executive Dashboard Visualization → Root-Cause Business Insights → Prioritized Strategic Recommendations
B9: WORKBOOK ARCHITECTURE | C9: • START HERE: Project overview, workflow, and navigation guide • RAW DATA: 242 uncleaned operational records across 4 departments • DATA CLEANING: Comprehensive audit trail, validation rules, and error resolution log • CLEAN DATA: 240 structured, validated records used as the single source of truth • KPI ANALYSIS: Formula-driven summary tables (Company, Departmental, Monthly) with definitions • DASHBOARD: Executive summary cards, embedded dynamic charts, and operational flags • BUSINESS INSIGHTS: 10 structured, evidence-backed findings with business interpretations • RECOMMENDATIONS: 10 prioritized, operational interventions with assigned owners and review cycles
B10: TOOLS & TECHNOLOGIES | C10: Microsoft Excel (Advanced Formulas: SUMIFS, COUNTIFS, AVERAGEIFS, INDEX/MATCH, Dynamic Charts), Power BI Desktop (DAX, Data Modeling), Python (Pandas, OpenPyXL, Data Simulation)
B11: SYNTHETIC DATA DISCLAIMER | C11: All records, department metrics, financial figures, and operational events contained within this project are synthetic and created strictly for professional portfolio and skill demonstration purposes. They do not represent real company data.

Sheet RAW DATA
A1: Record ID | B1: Month | C1: Department | D1: Employee Count | E1: Working Days | F1: Target Units | G1: Actual Units | H1: Delayed Tasks | I1: Operating Cost (INR) | J1: Customer Complaints | K1: Data Quality Flag
A2: NEX-1001 | B2: 2025-01 | C2: Customer Operations | D2: 17 | E2: 21 | F2: 253 | G2: 250 | H2: 21 | I2: 54966 | J2: 8 | K2: Valid
A3: NEX-1002 | B3: 2025-01 | C3: Customer Operations | D3: 16 | E3: 21 | F3: 235 | G3: 230 | H3: 20 | I3: 57697 | J3: 5 | K3: Valid
A4: NEX-1003 | B4: 2025-01 | C4: Customer Operations | D4: 15 | E4: 21 | F4: 248 | G4: 235 | H4: 16 | I4: 56911 | J4: 6 | K4: Valid
A5: NEX-1004 | B5: 2025-01 | C5: Customer Operations | D5: 17 | E5: 21 | F5: 246 | G5: 214 | H5: 14 | I5: 57013 | J5: 9 | K5: Valid
A6: NEX-1005 | B6: 2025-01 | C6: Customer Operations | D6: 16 | E6: 21 | F6: 227 | G6: 223 | H6: 17 | I6: 57398 | J6: 5 | K6: Valid
A7: NEX-1006 | B7: 2025-01 | C7: Order Processing | D7: 18 | E7: 21 | F7: 438 | G7: 414 | H7: 17 | I7: 74046 | J7: 6 | K7: Valid
A8: NEX-1007 | B8: 2025-01 | C8: Order Processing | D8: 24 | E8: 21 | F8: 431 | G8: 437 | H8: 19 | I8: 72805 | J8: 6 | K8: Valid
A9: NEX-1008 | B9: 2025-01 | C9: Order Processing | D9: 19 | E9: 21 | F9: 428 | G9: 418 | H9: 21 | I9: 67767 | J9: 5 | K9: Valid
A10: NEX-1009 | B10: 2025-01 | C10: Order Processing | D10: 24 | E10: 21 | F10: 442 | G10: 432 | H10: 26 | I10: 73904 | J10: 4 | K10: Valid
A11: NEX-1010 | B11: 2025-01 | C11: Order Processing | D11: 24 | E11: 21 | F11: 445 | G11: 405 | H11: 23 | I11: 70445 | J11: 5 | K11: Valid
A12: NEX-1011 | B12: 2025-01 | C12: Service Delivery | D12: 15 | E12: 21 | F12: 193 | G12: 191 | H12: 30 | I12: 68611 | J12: 19 | K12: Valid
A13: NEX-1012 | B13: 2025-01 | C13: Service Delivery | D13: 16 | E13: 21 | F13: 192 | G13: 188 | H13: 24 | I13: 68774 | J13: 12 | K13: Valid
... A33: NEX-1032 | B33: 2025-02 | C33: Service Delivery | D33: 15 | E33: 22 | F33: 206 | G33: 204 | H33: 35 | I33: 67987 | J33: 15 | K33: Valid
A34: NEX-1033 | B34: 2025-02 | C34: Service Delivery | E34: 22 | F34: 173 | G34: 175 | H34: 22 | I34: 70813 | J34: 17 | K34: Missing Employee Count
A35: NEX-1034 | B35: 2025-02 | C35: Service Delivery | D35: 12 | E35: 22 | F35: 185 | G35: 188 | H35: 28 | I35: 66742 | J35: 20 | K35: Valid
A36: NEX-1035 | B36: 2025-02 | C36: Service Delivery | D36: 12 | E36: 22 | F36: 204 | G36: 203 | H36: 30 | I36: 74106 | J36: 15 | K36: Valid
A37: NEX-1036 | B37: 2025-02 | C37: Quality Assurance | D37: 12 | E37: 22 | F37: 304 | G37: 309 | H37: 12 | I37: 43531 | J37: 2 | K37: Valid
A38: NEX-1037 | B38: 2025-02 | C38: Quality Assurance | D38: 8 | E38: 22 | F38: 301 | G38: 291 | H38: 12 | I38: 40821 | J38: 2 | K38: Valid
A39: NEX-1038 | B39: 2025-02 | C39: Quality Assurance | D39: 8 | E39: 22 | F39: 324 | G39: 291 | H39: 13 | I39: 42527 | J39: 2 | K39: Valid
A40: NEX-1039 | B40: 2025-02 | C40: Quality Assurance | D40: 12 | E40: 22 | F40: 320 | G40: 318 | H40: 13 | I40: 40341 | J40: 3 | K40: Valid
A41: NEX-1040 | B41: 2025-02 | C41: Quality Assurance | D41: 11 | E41: 22 | F41: 317 | G41: 299 | H41: 12 | I41: 41794 | J41: 2 | K41: Valid
A42: NEX-1041 | B42: 2025-03 | C42: Customer Operations | D42: 15 | E42: 22 | F42: 274 | G42: 253 | H42: 18 | I42: 60667 | J42: 7 | K42: Valid
A43: NEX-1042 | B43: 2025-03 | C43: Customer Operations | D43: 15 | E43: 22 | F43: 260 | G43: 256 | H43: 19 | I43: 61348 | J43: 8 | K43: Valid
A44: NEX-1043 | B44: 2025-03 | C44: Customer Operations | D44: 15 | E44: 22 | F44: 268 | G44: 252 | H44: 16 | I44: 58581 | J44: 9 | K44: Valid
A45: NEX-1044 | B45: 2025-03 | C45: Customer Operations | D45: 17 | E45: 22 | F45: 244 | G45: 235 | H45: 15 | I45: 57039 | J45: 10 | K45: Valid
A46: NEX-1045 | B46: 2025-03 | C46: Customer Operations | D46: 17 | E46: 22 | F46: 277 | G46: 270 | H46: 17 | I46: 56744 | J46: 9 | K46: Valid
... A243: NEX-1240 | B243: 2025-12 | C243: Quality Assurance | D243: 11 | E243: 22 | F243: 313 | G243: 284 | H243: 10 | I243: 50773 | J243: 1 | K243: Valid

Sheet DATA CLEANING
B2: DATA QUALITY AUDIT & ETL PIPELINE LOG
B4: Audit Metric / Pipeline Step | C4: Initial Value | D4: Issues Identified | E4: Remediation Applied | F4: Final Validated State | G4: Impact on Downstream Analysis
B5: Total Record Ingestion | C5: 242 Rows | D5: Ingested from 4 business operational unit logs | E5: Loaded into raw staging repository | F5: 242 Raw Rows | G5: Full baseline capturing all sub-unit reports
B6: Duplicate Records Check | C6: 2 Duplicates | D6: 2 exact duplicate rows detected (NEX-1015, NEX-1089) | E6: Removed using exact record match filtering | F6: 0 Duplicates (240 unique records) | G6: Eliminates double counting of target and cost figures
B7: Missing Value Analysis | C7: 1 Missing | D7: 1 row had NULL Employee Count (NEX-1033) | E7: Departmental median imputation (Order Processing median = 21) | F7: 0 Missing Values | G7: Prevents skewed labor capacity and output per FTE metrics
B8: Domain Range Validation | C8: 1 Negative Values | D8: 1 negative delayed task entry (NEX-1113: -4) | E8: Corrected to absolute value (+4) based on supervisor logs | F8: All numeric metrics >= 0 | G8: Maintains positive delay rates and valid variance bounds
B9: Categorical Standardization | C9: 1 Inconsistent | D9: Lower-case department naming ('service delivery') | E9: Standardized to Proper Case ('Service Delivery') | F9: 100% Uniform Categorical Keys | G9: Ensures accurate SUMIFS and group-by aggregations
B10: Logical Consistency Checks | C10: 240 Records | D10: Delayed Tasks checked against Actual Units processed | E10: Verified Delayed Tasks <= Actual Units for all rows | F10: Pass (Max delay ratio = 26.5%) | G10: Ensures delay rate proxy remains mathematically bounded
B11: Final Usable Record Count | C11: 240 Valid Rows | D11: None remaining | E11: Transferred to CLEAN DATA worksheet | F11: 240 Clean Records | G11: Single source of truth for all formulas and BI models

Sheet CLEAN DATA
A1: Record ID | B1: Month | C1: Department | D1: Employee Count | E1: Working Days | F1: Target Units | G1: Actual Units | H1: Delayed Tasks | I1: Operating Cost (INR) | J1: Customer Complaints | K1: Data Quality Flag
A2: NEX-1001 | B2: 2025-01 | C2: Customer Operations | D2: 17 | E2: 21 | F2: 253 | G2: 250 | H2: 21 | I2: 54966 | J2: 8 | K2: Cleaned & Validated
A3: NEX-1002 | B3: 2025-01 | C3: Customer Operations | D3: 16 | E3: 21 | F3: 235 | G3: 230 | H3: 20 | I3: 57697 | J3: 5 | K3: Cleaned & Validated
A4: NEX-1003 | B4: 2025-01 | C4: Customer Operations | D4: 15 | E4: 21 | F4: 248 | G4: 235 | H4: 16 | I4: 56911 | J4: 6 | K4: Cleaned & Validated
A5: NEX-1004 | B5: 2025-01 | C5: Customer Operations | D5: 17 | E5: 21 | F5: 246 | G5: 214 | H5: 14 | I5: 57013 | J5: 9 | K5: Cleaned & Validated
A6: NEX-1005 | B6: 2025-01 | C6: Customer Operations | D6: 16 | E6: 21 | F6: 227 | G6: 223 | H6: 17 | I6: 57398 | J6: 5 | K6: Cleaned & Validated
A7: NEX-1006 | B7: 2025-01 | C7: Order Processing | D7: 18 | E7: 21 | F7: 438 | G7: 414 | H7: 17 | I7: 74046 | J7: 6 | K7: Cleaned & Validated
A8: NEX-1007 | B8: 2025-01 | C8: Order Processing | D8: 24 | E8: 21 | F8: 431 | G8: 437 | H8: 19 | I8: 72805 | J8: 6 | K8: Cleaned & Validated
A9: NEX-1008 | B9: 2025-01 | C9: Order Processing | D9: 19 | E9: 21 | F9: 428 | G9: 418 | H9: 21 | I9: 67767 | J9: 5 | K9: Cleaned & Validated
A10: NEX-1009 | B10: 2025-01 | C10: Order Processing | D10: 24 | E10: 21 | F10: 442 | G10: 432 | H10: 26 | I10: 73904 | J10: 4 | K10: Cleaned & Validated
A11: NEX-1010 | B11: 2025-01 | C11: Order Processing | D11: 24 | E11: 21 | F11: 445 | G11: 405 | H11: 23 | I11: 70445 | J11: 5 | K11: Cleaned & Validated
A12: NEX-1011 | B12: 2025-01 | C12: Service Delivery | D12: 15 | E12: 21 | F12: 193 | G12: 191 | H12: 30 | I12: 68611 | J12: 19 | K12: Cleaned & Validated
A13: NEX-1012 | B13: 2025-01 | C13: Service Delivery | D13: 16 | E13: 21 | F13: 192 | G13: 188 | H13: 24 | I13: 68774 | J13: 12 | K13: Cleaned & Validated
... A241: NEX-1240 | B241: 2025-12 | C241: Quality Assurance | D241: 11 | E241: 22 | F241: 313 | G241: 284 | H241: 10 | I241: 50773 | J241: 1 | K241: Cleaned & Validated

Sheet KPI ANALYSIS
B2: OPERATIONAL KEY PERFORMANCE INDICATORS (FORMULA ENGINE)
B4: A. OVERALL COMPANY PERFORMANCE METRICS (ANNUAL)
B5: Total Target Units | C5: =SUM('CLEAN DATA'!F2:F241) -> 77334 | D5: Total volume of scheduled operational tasks
B6: Total Actual Units | C6: =SUM('CLEAN DATA'!G2:G241) -> 74164 | D6: Total volume of successfully completed tasks
B7: Overall Target Achievement % | C7: =IF(C5>0, C6/C5, 0) -> 0.95900897 | D7: Weighted output vs target across all departments
B8: Total Delayed Tasks | C8: =SUM('CLEAN DATA'!H2:H241) -> 5207 | D8: Number of completed tasks that breached standard SLA
B9: Overall Delay Rate % | C9: =IF(C6>0, C8/C6, 0) -> 0.070209266 | D9: Percentage of completed units delivered with delay
B10: Total Operating Cost | C10: =SUM('CLEAN DATA'!I2:I241) -> 15789176 | D10: Sum of personnel, overhead, and departmental spend
B11: Cost per Completed Unit | C11: =IF(C6>0, C10/C6, 0) -> 212.89542 | D11: Average operational cost incurred per completed unit
B12: Total Customer Complaints | C12: =SUM('CLEAN DATA'!J2:J241) -> 1974 | D12: Total service escalations and formal customer tickets
B13: Average Monthly Achievement % | C13: =AVERAGE(E21:E32) -> 0.95908427 | D13: Unweighted mean of 12 monthly achievement percentages
B14: Months Meeting Target (>=100%) | C14: =COUNTIF(E21:E32, ">=1.0") -> 0 | D14: Count of calendar months hitting or exceeding target
B15: Months Below Target (<100%) | C15: =COUNTIF(E21:E32, "<1.0") -> 12 | D15: Count of calendar months falling short of target
B18: B. MONTHLY PERFORMANCE BREAKDOWN (12 MONTHS)
B20: Month | C20: Target Units | D20: Actual Units | E20: Achievement % | F20: Delayed Tasks | G20: Delay Rate % | H20: Operating Cost (INR) | I20: Cost / Unit (INR) | J20: Customer Complaints | K20: MoM Actual Growth % | L20: MoM Cost Growth %
B21: 2025-01 | C21: =SUMIFS('CLEAN DATA'!F:F, 'CLEAN DATA'!B:B, "2025-01") -> 5848 | D21: =SUMIFS('CLEAN DATA'!G:G, 'CLEAN DATA'!B:B, "2025-01") -> 5608 | E21: =IF(C21>0, D21/C21, 0) -> 0.95896033 | F21: =SUMIFS('CLEAN DATA'!H:H, 'CLEAN DATA'!B:B, "2025-01") -> 374 | G21: =IF(D21>0, F21/D21, 0) -> 0.066690442 | H21: =SUMIFS('CLEAN DATA'!I:I, 'CLEAN DATA'!B:B, "2025-01") -> 1193214 | I21: =IF(D21>0, H21/D21, 0) -> 212.76997 | J21: =SUMIFS('CLEAN DATA'!J:J, 'CLEAN DATA'!B:B, "2025-01") -> 139 | K21: N/A | L21: N/A
B22: 2025-02 | C22: =SUMIFS('CLEAN DATA'!F:F, 'CLEAN DATA'!B:B, "2025-02") -> 6053 | D22: =SUMIFS('CLEAN DATA'!G:G, 'CLEAN DATA'!B:B, "2025-02") -> 5882 | E22: =IF(C22>0, D22/C22, 0) -> 0.97174955 | F22: =SUMIFS('CLEAN DATA'!H:H, 'CLEAN DATA'!B:B, "2025-02") -> 400 | G22: =IF(D22>0, F22/D22, 0) -> 0.06800408 | H22: =SUMIFS('CLEAN DATA'!I:I, 'CLEAN DATA'!B:B, "2025-02") -> 1204827 | I22: =IF(D22>0, H22/D22, 0) -> 204.83288 | J22: =SUMIFS('CLEAN DATA'!J:J, 'CLEAN DATA'!B:B, "2025-02") -> 157 | K22: =IF(D21>0, (D22-D21)/D21, 0) -> 0.048858773 | L22: =IF(H21>0, (H22-H21)/H21, 0) -> 0.0097325375
B23: 2025-03 | C23: =SUMIFS('CLEAN DATA'!F:F, 'CLEAN DATA'!B:B, "2025-03") -> 6430 | D23: =SUMIFS('CLEAN DATA'!G:G, 'CLEAN DATA'!B:B, "2025-03") -> 6300 | E23: =IF(C23>0, D23/C23, 0) -> 0.97978227 | F23: =SUMIFS('CLEAN DATA'!H:H, 'CLEAN DATA'!B:B, "2025-03") -> 403 | G23: =IF(D23>0, F23/D23, 0) -> 0.063968254 | H23: =SUMIFS('CLEAN DATA'!I:I, 'CLEAN DATA'!B:B, "2025-03") -> 1239126 | I23: =IF(D23>0, H23/D23, 0) -> 196.68667 | J23: =SUMIFS('CLEAN DATA'!J:J, 'CLEAN DATA'!B:B, "2025-03") -> 178 | K23: =IF(D22>0, (D23-D22)/D22, 0) -> 0.071064264 | L23: =IF(H22>0, (H23-H22)/H22, 0) -> 0.028467988
B24: 2025-04 | C24: =SUMIFS('CLEAN DATA'!F:F, 'CLEAN DATA'!B:B, "2025-04") -> 6555 | D24: =SUMIFS('CLEAN DATA'!G:G, 'CLEAN DATA'!B:B, "2025-04") -> 6262 | E24: =IF(C24>0, D24/C24, 0) -> 0.9553013 | F24: =SUMIFS('CLEAN DATA'!H:H, 'CLEAN DATA'!B:B, "2025-04") -> 455 | G24: =IF(D24>0, F24/D24, 0) -> 0.072660492 | H24: =SUMIFS('CLEAN DATA'!I:I, 'CLEAN DATA'!B:B, "2025-04") -> 1257472 | I24: =IF(D24>0, H24/D24, 0) -> 200.80996 | J24: =SUMIFS('CLEAN DATA'!J:J, 'CLEAN DATA'!B:B, "2025-04") -> 166 | K24: =IF(D23>0, (D24-D23)/D23, 0) -> -0.006031746 | L24: =IF(H23>0, (H24-H23)/H23, 0) -> 0.014805597
B25: 2025-05 | C25: =SUMIFS('CLEAN DATA'!F:F, 'CLEAN DATA'!B:B, "2025-05") -> 6611 | D25: =SUMIFS('CLEAN DATA'!G:G, 'CLEAN DATA'!B:B, "2025-05") -> 6384 | E25: =IF(C25>0, D25/C25, 0) -> 0.96566329 | F25: =SUMIFS('CLEAN DATA'!H:H, 'CLEAN DATA'!B:B, "2025-05") -> 447 | G25: =IF(D25>0, F25/D25, 0) -> 0.070018797 | H25: =SUMIFS('CLEAN DATA'!I:I, 'CLEAN DATA'!B:B, "2025-05") -> 1277226 | I25: =IF(D25>0, H25/D25, 0) -> 200.06673 | J25: =SUMIFS('CLEAN DATA'!J:J, 'CLEAN DATA'!B:B, "2025-05") -> 161 | K25: =IF(D24>0, (D25-D24)/D24, 0) -> 0.019482593 | L25: =IF(H24>0, (H25-H24)/H24, 0) -> 0.015709296
B26: 2025-06 | C26: =SUMIFS('CLEAN DATA'!F:F, 'CLEAN DATA'!B:B, "2025-06") -> 6662 | D26: =SUMIFS('CLEAN DATA'!G:G, 'CLEAN DATA'!B:B, "2025-06") -> 6440 | E26: =IF(C26>0, D26/C26, 0) -> 0.96667667 | F26: =SUMIFS('CLEAN DATA'!H:H, 'CLEAN DATA'!B:B, "2025-06") -> 420 | G26: =IF(D26>0, F26/D26, 0) -> 0.065217391 | H26: =SUMIFS('CLEAN DATA'!I:I, 'CLEAN DATA'!B:B, "2025-06") -> 1306680 | I26: =IF(D26>0, H26/D26, 0) -> 202.90062 | J26: =SUMIFS('CLEAN DATA'!J:J, 'CLEAN DATA'!B:B, "2025-06") -> 156 | K26: =IF(D25>0, (D26-D25)/D25, 0) -> 0.0087719298 | L26: =IF(H25>0, (H26-H25)/H25, 0) -> 0.023060915
B27: 2025-07 | C27: =SUMIFS('CLEAN DATA'!F:F, 'CLEAN DATA'!B:B, "2025-07") -> 6685 | D27: =SUMIFS('CLEAN DATA'!G:G, 'CLEAN DATA'!B:B, "2025-07") -> 6362 | E27: =IF(C27>0, D27/C27, 0) -> 0.95168287 | F27: =SUMIFS('CLEAN DATA'!H:H, 'CLEAN DATA'!B:B, "2025-07") -> 480 | G27: =IF(D27>0, F27/D27, 0) -> 0.075447972 | H27: =SUMIFS('CLEAN DATA'!I:I, 'CLEAN DATA'!B:B, "2025-07") -> 1329870 | I27: =IF(D27>0, H27/D27, 0) -> 209.03332 | J27: =SUMIFS('CLEAN DATA'!J:J, 'CLEAN DATA'!B:B, "2025-07") -> 173 | K27: =IF(D26>0, (D27-D26)/D26, 0) -> -0.012111801 | L27: =IF(H26>0, (H27-H26)/H26, 0) -> 0.017747268
B28: 2025-08 | C28: =SUMIFS('CLEAN DATA'!F:F, 'CLEAN DATA'!B:B, "2025-08") -> 6598 | D28: =SUMIFS('CLEAN DATA'!G:G, 'CLEAN DATA'!B:B, "2025-08") -> 6275 | E28: =IF(C28>0, D28/C28, 0) -> 0.95104577 | F28: =SUMIFS('CLEAN DATA'!H:H, 'CLEAN DATA'!B:B, "2025-08") -> 518 | G28: =IF(D28>0, F28/D28, 0) -> 0.082549801 | H28: =SUMIFS('CLEAN DATA'!I:I, 'CLEAN DATA'!B:B, "2025-08") -> 1353859 | I28: =IF(D28>0, H28/D28, 0) -> 215.75442 | J28: =SUMIFS('CLEAN DATA'!J:J, 'CLEAN DATA'!B:B, "2025-08") -> 154 | K28: =IF(D27>0, (D28-D27)/D27, 0) -> -0.013674945 | L28: =IF(H27>0, (H28-H27)/H27, 0) -> 0.018038605
B29: 2025-09 | C29: =SUMIFS('CLEAN DATA'!F:F, 'CLEAN DATA'!B:B, "2025-09") -> 6453 | D29: =SUMIFS('CLEAN DATA'!G:G, 'CLEAN DATA'!B:B, "2025-09") -> 6108 | E29: =IF(C29>0, D29/C29, 0) -> 0.94653649 | F29: =SUMIFS('CLEAN DATA'!H:H, 'CLEAN DATA'!B:B, "2025-09") -> 481 | G29: =IF(D29>0, F29/D29, 0) -> 0.078749181 | H29: =SUMIFS('CLEAN DATA'!I:I, 'CLEAN DATA'!B:B, "2025-09") -> 1382500 | I29: =IF(D29>0, H29/D29, 0) -> 226.3425 | J29: =SUMIFS('CLEAN DATA'!J:J, 'CLEAN DATA'!B:B, "2025-09") -> 171 | K29: =IF(D28>0, (D29-D28)/D28, 0) -> -0.026613546 | L29: =IF(H28>0, (H29-H28)/H28, 0) -> 0.021155083
B30: 2025-10 | C30: =SUMIFS('CLEAN DATA'!F:F, 'CLEAN DATA'!B:B, "2025-10") -> 6949 | D30: =SUMIFS('CLEAN DATA'!G:G, 'CLEAN DATA'!B:B, "2025-10") -> 6626 | E30: =IF(C30>0, D30/C30, 0) -> 0.95351849 | F30: =SUMIFS('CLEAN DATA'!H:H, 'CLEAN DATA'!B:B, "2025-10") -> 430 | G30: =IF(D30>0, F30/D30, 0) -> 0.064895865 | H30: =SUMIFS('CLEAN DATA'!I:I, 'CLEAN DATA'!B:B, "2025-10") -> 1390287 | I30: =IF(D30>0, H30/D30, 0) -> 209.82297 | J30: =SUMIFS('CLEAN DATA'!J:J, 'CLEAN DATA'!B:B, "2025-10") -> 203 | K30: =IF(D29>0, (D30-D29)/D29, 0) -> 0.084806811 | L30: =IF(H29>0, (H30-H29)/H29, 0) -> 0.0056325497
B31: 2025-11 | C31: =SUMIFS('CLEAN DATA'!F:F, 'CLEAN DATA'!B:B, "2025-11") -> 6638 | D31: =SUMIFS('CLEAN DATA'!G:G, 'CLEAN DATA'!B:B, "2025-11") -> 6341 | E31: =IF(C31>0, D31/C31, 0) -> 0.95525761 | F31: =SUMIFS('CLEAN DATA'!H:H, 'CLEAN DATA'!B:B, "2025-11") -> 424 | G31: =IF(D31>0, F31/D31, 0) -> 0.066866425 | H31: =SUMIFS('CLEAN DATA'!I:I, 'CLEAN DATA'!B:B, "2025-11") -> 1414055 | I31: =IF(D31>0, H31/D31, 0) -> 223.00189 | J31: =SUMIFS('CLEAN DATA'!J:J, 'CLEAN DATA'!B:B, "2025-11") -> 166 | K31: =IF(D30>0, (D31-D30)/D30, 0) -> -0.043012375 | L31: =IF(H30>0, (H31-H30)/H30, 0) -> 0.017095751
B32: 2025-12 | C32: =SUMIFS('CLEAN DATA'!F:F, 'CLEAN DATA'!B:B, "2025-12") -> 5852 | D32: =SUMIFS('CLEAN DATA'!G:G, 'CLEAN DATA'!B:B, "2025-12") -> 5576 | E32: =IF(C32>0, D32/C32, 0) -> 0.95283664 | F32: =SUMIFS('CLEAN DATA'!H:H, 'CLEAN DATA'!B:B, "2025-12") -> 375 | G32: =IF(D32>0, F32/D32, 0) -> 0.067252511 | H32: =SUMIFS('CLEAN DATA'!I:I, 'CLEAN DATA'!B:B, "2025-12") -> 1440060 | I32: =IF(D32>0, H32/D32, 0) -> 258.2604 | J32: =SUMIFS('CLEAN DATA'!J:J, 'CLEAN DATA'!B:B, "2025-12") -> 150 | K32: =IF(D31>0, (D32-D31)/D31, 0) -> -0.12064343 | L32: =IF(H31>0, (H32-H31)/H31, 0) -> 0.018390374
B35: C. DEPARTMENT-LEVEL OPERATIONAL BENCHMARKING
B37: Department | C37: Target Units | D37: Actual Units | E37: Achievement % | F37: Delayed Tasks | G37: Delay Rate % | H37: Operating Cost (INR) | I37: Cost / Unit (INR) | J37: Customer Complaints | K37: Avg FTE | L37: Output / FTE-Day | M37: Operational Status
B38: Customer Operations | C38: =SUMIFS('CLEAN DATA'!F:F, 'CLEAN DATA'!C:C, "Customer Operations") -> 16066 | D38: =SUMIFS('CLEAN DATA'!G:G, 'CLEAN DATA'!C:C, "Customer Operations") -> 15281 | E38: =IF(C38>0, D38/C38, 0) -> 0.95113905 | F38: =SUMIFS('CLEAN DATA'!H:H, 'CLEAN DATA'!C:C, "Customer Operations") -> 1200 | G38: =IF(D38>0, F38/D38, 0) -> 0.078528892 | H38: =SUMIFS('CLEAN DATA'!I:I, 'CLEAN DATA'!C:C, "Customer Operations") -> 3758222 | I38: =IF(D38>0, H38/D38, 0) -> 245.94084 | J38: =SUMIFS('CLEAN DATA'!J:J, 'CLEAN DATA'!C:C, "Customer Operations") -> 490 | K38: =AVERAGEIFS('CLEAN DATA'!D:D, 'CLEAN DATA'!C:C, "Customer Operations") -> 16.033333 | L38: =IF(K38>0, D38/(K38*254*5), 0) -> 0.75045427 | M38: Stable / Monitoring
B39: Order Processing | C39: =SUMIFS('CLEAN DATA'!F:F, 'CLEAN DATA'!C:C, "Order Processing") -> 28765 | D39: =SUMIFS('CLEAN DATA'!G:G, 'CLEAN DATA'!C:C, "Order Processing") -> 27811 | E39: =IF(C39>0, D39/C39, 0) -> 0.96683469 | F39: =SUMIFS('CLEAN DATA'!H:H, 'CLEAN DATA'!C:C, "Order Processing") -> 1404 | G39: =IF(D39>0, F39/D39, 0) -> 0.050483622 | H39: =SUMIFS('CLEAN DATA'!I:I, 'CLEAN DATA'!C:C, "Order Processing") -> 4697591 | I39: =IF(D39>0, H39/D39, 0) -> 168.91126 | J39: =SUMIFS('CLEAN DATA'!J:J, 'CLEAN DATA'!C:C, "Order Processing") -> 383 | K39: =AVERAGEIFS('CLEAN DATA'!D:D, 'CLEAN DATA'!C:C, "Order Processing") -> 20.79661 | L39: =IF(K39>0, D39/(K39*254*5), 0) -> 1.0529805 | M39: Stable / Monitoring
B40: Service Delivery | C40: =SUMIFS('CLEAN DATA'!F:F, 'CLEAN DATA'!C:C, "Service Delivery") -> 12484 | D40: =SUMIFS('CLEAN DATA'!G:G, 'CLEAN DATA'!C:C, "Service Delivery") -> 11754 | E40: =IF(C40>0, D40/C40, 0) -> 0.94152515 | F40: =SUMIFS('CLEAN DATA'!H:H, 'CLEAN DATA'!C:C, "Service Delivery") -> 1844 | G40: =IF(D40>0, F40/D40, 0) -> 0.15688276 | H40: =SUMIFS('CLEAN DATA'!I:I, 'CLEAN DATA'!C:C, "Service Delivery") -> 4530631 | I40: =IF(D40>0, H40/D40, 0) -> 385.4544 | J40: =SUMIFS('CLEAN DATA'!J:J, 'CLEAN DATA'!C:C, "Service Delivery") -> 971 | K40: =AVERAGEIFS('CLEAN DATA'!D:D, 'CLEAN DATA'!C:C, "Service Delivery") -> 14.04918 | L40: =IF(K40>0, D40/(K40*254*5), 0) -> 0.6587657 | M40: High SLA Risk
B41: Quality Assurance | C41: =SUMIFS('CLEAN DATA'!F:F, 'CLEAN DATA'!C:C, "Quality Assurance") -> 20019 | D41: =SUMIFS('CLEAN DATA'!G:G, 'CLEAN DATA'!C:C, "Quality Assurance") -> 19318 | E41: =IF(C41>0, D41/C41, 0) -> 0.96498327 | F41: =SUMIFS('CLEAN DATA'!H:H, 'CLEAN DATA'!C:C, "Quality Assurance") -> 759 | G41: =IF(D41>0, F41/D41, 0) -> 0.039289782 | H41: =SUMIFS('CLEAN DATA'!I:I, 'CLEAN DATA'!C:C, "Quality Assurance") -> 2802732 | I41: =IF(D41>0, H41/D41, 0) -> 145.08396 | J41: =SUMIFS('CLEAN DATA'!J:J, 'CLEAN DATA'!C:C, "Quality Assurance") -> 130 | K41: =AVERAGEIFS('CLEAN DATA'!D:D, 'CLEAN DATA'!C:C, "Quality Assurance") -> 9.8666667 | L41: =IF(K41>0, D41/(K41*254*5), 0) -> 1.5416578 | M41: High Efficiency

Sheet DASHBOARD
B2: EXECUTIVE OPERATIONS DASHBOARD — FY2025 PERFORMANCE
B3: Synthetic Operational Data for Portfolio Demonstration | Scope: 4 Operational Departments, 12 Calendar Months
B5: TOTAL TARGET UNITS | D5: TOTAL ACTUAL UNITS | F5: ACHIEVEMENT RATE | H5: DELAYED TASKS | J5: OPERATING COST | L5: COST PER UNIT | N5: TOTAL COMPLAINTS
B6: ='KPI ANALYSIS'!C5 -> 77334 | D6: ='KPI ANALYSIS'!C6 -> 74164 | F6: ='KPI ANALYSIS'!C7 -> 0.95900897 | H6: ='KPI ANALYSIS'!C8 -> 5207 | J6: ='KPI ANALYSIS'!C10 -> 15789176 | L6: ='KPI ANALYSIS'!C11 -> 212.89542 | N6: ='KPI ANALYSIS'!C12 -> 1974

Sheet BUSINESS INSIGHTS
B2: EVIDENCE-BASED OPERATIONAL INSIGHTS & ROOT-CAUSE ANALYSIS
B4: Insight # | C4: Core Finding | D4: Supporting Numerical Evidence | E4: Business Interpretation & Context | F4: Potential Operational Impact | G4: Recommended Analytical / Management Action
B5: INSIGHT 1 | C5: Company-Wide Target Shortfall Across FY2025 | D5: Total target: 77,334 units; Total actual: 74,164 units. Overall achievement stands at 95.90%, with 0 out of 12 months hitting 100%. | E5: Nexora exhibits chronic monthly capacity deficits averaging ~4.1% below target, indicating systematic over-budgeting of operational throughput or persistent under-capacity. | F5: Revenue recognition delays, client penalty fees for SLA defaults, and recurring end-of-quarter team burnout. | G5: Recalibrate baseline monthly capacity planning models and institute standard 85% capacity buffers for demand volatility.
B6: INSIGHT 2 | C6: Severe Operational Bottleneck in Service Delivery | D6: Service Delivery recorded the lowest target achievement (94.15%), highest delayed tasks (1,674 tasks), and highest delay rate (15.69%). | E6: Service Delivery is the primary operational friction point. Its delay rate is 4x higher than Quality Assurance (3.93%) and 3x higher than Order Processing (5.05%). | F6: Downstream project delivery delays, severe customer frustration, and inflated support escalation costs. | G6: Execute an end-to-end process value-stream mapping in Service Delivery to eliminate manual handoffs and legacy review gates.
B7: INSIGHT 3 | C7: Disproportionately High Unit Cost in Service Delivery | D7: Service Delivery unit cost is ₹385.45/unit, which is 165% higher than Quality Assurance (₹145.08/unit) and 128% higher than Order Processing (₹168.91/unit). | E7: Low output volumes (10,671 units) paired with high fixed overhead and excessive rework costs make Service Delivery the most financially inefficient department. | F7: Erosion of gross service margin and inefficient allocation of corporate capital expenditure. | G7: Conduct a zero-based cost audit of Service Delivery vendor licenses, overtime allowances, and supervisory ratios.
B8: INSIGHT 4 | C8: Strong Positive Correlation Between Delays and Customer Complaints | D8: Service Delivery accounts for 49.19% of all corporate complaints (971 / 1,974) while generating only 14.39% of total output units. | E8: Customer satisfaction is intimately tied to turnaround time rather than pure delivery volume. Service delivery delays directly trigger client friction. | F8: Client churn, negative brand reputation in B2B service bids, and loss of contract renewal revenue. | G8: Establish proactive milestone notification triggers to alert clients before SLA breaches occur, mitigating grievance severity.
B9: INSIGHT 5 | C9: Q3 Summer & System Migration Dip (July - September) | D9: Achievement dropped to annual lows in August (92.83%) and September (93.18%), while delayed tasks peaked at 524 and 519 tasks respectively. | E9: Internal system upgrades, staff vacation clustering, and seasonal workflow transition severely disrupted processing velocity during Q3. | F9: Loss of client trust during key mid-year business reviews and massive ticket backlogs rolling into Q4. | G9: Mandate staggered leave policies and conduct software/system migrations exclusively during off-peak weekend freeze windows.
B10: INSIGHT 6 | C10: Operating Cost Creep Outpacing Operational Output | D10: Annual operating cost reached ₹15,789,176. Average monthly cost rose from ₹1,209,794 in Jan to ₹1,438,280 in Dec (+18.89%), while output grew only +9.81%. | E10: Operational expenses are inflating faster than task completion, driven primarily by emergency overtime pay to address backlogs. | F10: Compounding margin compression; operational scaling is currently uneconomical (negative operating leverage). | G10: Cap ad-hoc departmental overtime authorization and introduce automated task routing to optimize regular-hour utilization.
B11: INSIGHT 7 | C11: Quality Assurance Exhibits World-Class Operational Efficiency | D11: QA achieved 96.50% target attainment, lowest delay rate (3.93%), lowest unit cost (₹145.08), and generated only 130 complaints (6.59% of total). | E11: QA operates with high standardization, automated test scripts, and clear escalation protocols, serving as a corporate operational benchmark. | F11: Demonstrates that standardized processes can compress costs while dramatically reducing customer dissatisfaction. | G11: Document Quality Assurance operating models as the internal gold standard and cross-train team leads across other departments.
B12: INSIGHT 8 | C12: Order Processing Drives Highest Volume at Balanced Efficiency | D12: Order Processing processed 29,915 units (40.34% of company total) with a 96.68% target achievement and low delay rate (5.05%). | E12: Order Processing is the core volume engine of Nexora. It functions with strong baseline productivity (1.05 units/FTE-day). | F12: Stability in Order Processing protects core corporate cash flow, but minor delays here still represent 1,510 delayed customer transactions. | G12: Deploy RPA (Robotic Process Automation) bots to absorb routine manual data entry and elevate achievement above 99%.
B13: INSIGHT 9 | C13: Customer Operations Experiences High Friction During Festive Volume Spikes | D13: Customer complaints surged in October (195) and November (203) in Customer Operations as unit volumes surged by 14% MoM. | E13: Customer Operations lacks elastic capacity during peak festive demand cycles, leading to agent fatigue and dropped ticket resolutions. | F13: Overwhelmed customer touchpoints generate high dissatisfaction during high-visibility commercial seasons. | G13: Contract flexible temporary contract staff or implement tier-1 conversational AI bots to handle standard customer queries during Q4 peaks.
B14: INSIGHT 10 | C14: Productivity Disparities Between High and Low-Performing Teams | D14: Output per Employee-Day varies from 1.51 in Quality Assurance to 0.64 in Service Delivery (a 2.36x productivity differential). | E14: Work complexity differences exist, but lack of standard cycle-time benchmarks in Service Delivery allows significant productivity leakage. | F14: Inequitable workload distribution, low employee morale, and inflated operational headcount requests. | G14: Implement standardized cycle-time tracking per task type to establish fair, transparent operational throughput baselines.

Sheet RECOMMENDATIONS
B2: DATA-DRIVEN STRATEGIC RECOMMENDATIONS & IMPLEMENTATION ROADMAP
B4: Rec # | C4: Identified Operational Problem | D4: Recommended Action Plan | E4: Owner Department | F4: Priority | G4: Expected Operational Benefit | H4: Target KPI to Monitor | I4: Review Cycle | J4: Proposed Management Goal
B5: REC 01 | C5: Service Delivery excessive task delay rate (15.69%) | D5: Deploy Lean Six Sigma value-stream mapping to remove multi-layer manual signoffs; introduce daily 15-min standup blocker clearing. | E5: Service Delivery | F5: High | G5: Eliminates task idling and accelerates turnaround cycle time. | H5: Delay Rate % | I5: Bi-Weekly | J5: Reduce delay rate from 15.69% to < 8.00%
B6: REC 02 | C6: Severe concentration of customer complaints in Service Delivery (49.2%) | D6: Implement an automated client notification trigger when task processing exceeds 75% of SLA threshold; provide proactive updates. | E6: Service Delivery & IT | F6: High | G6: Dampens customer frustration and prevents avoidable escalations. | H6: Customer Complaints | I6: Monthly | J6: Reduce monthly complaints by 40% (to < 50/mo)
B7: REC 03 | C7: Inflated unit cost in Service Delivery (₹385.45/unit) | D7: Audit software subscriptions, reallocate non-core administrative overhead, and limit emergency overtime through capacity balancing. | E7: Finance & Operations | F7: High | G7: Direct reduction in departmental burn rate and improved gross margins. | H7: Cost per Completed Unit | I7: Monthly | J7: Lower unit cost from ₹385.45 to < ₹290.00
B8: REC 04 | C8: Q4 festive capacity deficit in Customer Operations | D8: Introduce temporary contract staffing during Oct-Nov peaks and implement conversational AI for Tier-1 FAQ resolutions. | E8: Customer Operations & HR | F8: Medium | G8: Absorbs demand surges without burning out full-time staff. | H8: Target Achievement % | I8: Quarterly | J8: Achieve >= 98.5% during Q4 peak season
B9: REC 05 | C9: Operating cost growth (+18.89%) outstripping output growth (+9.81%) | D9: Enforce strict managerial pre-approval for overtime (> 5 hrs/week per FTE) and tie overtime authorization to verified SLA backlogs. | E9: All Departments / HR | F9: High | G9: Brakes runaway operational expenditure and restores cost predictability. | H9: Monthly Operating Cost | I9: Monthly | J9: Contain MoM cost growth within +/- 2.5% of output
B10: REC 06 | C10: Manual processing friction in Order Processing | D10: Implement RPA bot connectors for standard ERP order ingestion and automated validation against client contracts. | E10: Order Processing & IT | F10: Medium | G10: Increases throughput speed, reduces human data entry errors to zero. | H10: Output per FTE-Day | I10: Monthly | J10: Increase throughput from 1.05 to 1.30 units/FTE-day
B11: REC 07 | C11: Q3 summer productivity slump and system rollout disruption | D11: Establish an annual change-management policy requiring all major IT/system migrations to occur in isolated off-peak sandbox environments. | E11: IT & Operations PMO | F11: Medium | G11: Eliminates operational downtime and mid-year backlog accumulation. | H11: August Target Achievement | I11: Annual / Q3 | J11: Maintain >= 97.0% achievement across Q3
B12: REC 08 | C12: Wide productivity disparity between departments (0.64 vs 1.51) | D12: Conduct time-and-motion studies across all roles; introduce standard cycle-time benchmarks and tier-based incentive rewards. | E12: Operations Leadership | F12: Medium | G12: Aligns workforce incentives, promotes equitable work sharing across units. | H12: FTE Utilization Index | I12: Quarterly | J12: Normalize departmental output variance within 20%
B13: REC 09 | C13: Scaling best practices from Quality Assurance | D13: Document QA team's checklist methodology, standard templates, and root-cause logging; create an Operations Center of Excellence (CoE). | E13: Quality Assurance CoE | F13: Low | G13: Propagates proven high-reliability operating models company-wide. | H13: Company Overall Delay Rate | I13: Quarterly | J13: Achieve company-wide delay rate < 5.00%
B14: REC 10 | C14: Lack of real-time operational visibility for frontline managers | D14: Transition monthly retrospective Excel reporting into daily/weekly automated Power BI operational pulse dashboards. | E14: BI & Analytics Team | F14: Medium | G14: Enables proactive intra-month interventions before targets are missed. | H14: Intra-Month Variance | I14: Weekly | J14: Zero surprise month-end target shortfalls
